task3/group8/rtl/loa_adder.v
`timescale 1 ns / 1 ps

module loa_adder #(
	parameter integer WIDTH = 32,
	parameter integer K = 4
) (
	input  [WIDTH-1:0] a,
	input  [WIDTH-1:0] b,
	output [WIDTH-1:0] sum,
	output             carry_out
);
	initial begin
		if (K <= 0 || K >= WIDTH) begin
			$display("ERROR: loa_adder requires 0 < K < WIDTH. WIDTH=%0d K=%0d", WIDTH, K);
			$finish;
		end
	end

	wire [K-1:0] lower_sum;
	wire         lower_carry;
	wire [WIDTH-K:0] upper_sum_ext;

	assign lower_sum = a[K-1:0] | b[K-1:0];
	assign lower_carry = a[K-1] & b[K-1];
	assign upper_sum_ext = {1'b0, a[WIDTH-1:K]} + {1'b0, b[WIDTH-1:K]} + lower_carry;

	assign sum[K-1:0] = lower_sum;
	assign sum[WIDTH-1:K] = upper_sum_ext[WIDTH-K-1:0];
	assign carry_out = upper_sum_ext[WIDTH-K];
endmodule

group8/rtl/v2_8x8_multiplier.v
`timescale 1 ns / 1 ps

module v2_8x8_multiplier #(
	parameter [8*22-1:0] V2_IMPLEMENTATION = "BEST_EFFORT_22"
) (
	input  [7:0] a,
	input  [7:0] b,
	output [15:0] p
);
	// Best-effort Group-8 construction for the 22 block:
	// - split the 8x8 multiplication into two 8x4 groups using b[3:0] and b[7:4]
	// - approximate each group by clearing its two least-significant local bits
	// - accumulate the two groups in the standard shifted form
	//
	// This matches the available information that the 22 architecture uses two
	// approximated positions in each of the lower-order and higher-order groups.
	// Replace this model with the exact course-provided 22/V2 cell placement if a
	// precise block diagram becomes available.
	wire [11:0] group_a_exact;
	wire [11:0] group_b_exact;
	wire [11:0] group_a_approx;
	wire [11:0] group_b_approx;
	wire [11:0] group_a_row0;
	wire [11:0] group_a_row1;
	wire [11:0] group_a_row2;
	wire [11:0] group_a_row3;
	wire [11:0] group_b_row0;
	wire [11:0] group_b_row1;
	wire [11:0] group_b_row2;
	wire [11:0] group_b_row3;

	assign group_a_row0 = b[0] ? {4'b0000, a}       : 12'b0;
	assign group_a_row1 = b[1] ? {3'b000, a, 1'b0} : 12'b0;
	assign group_a_row2 = b[2] ? {2'b00, a, 2'b00} : 12'b0;
	assign group_a_row3 = b[3] ? {1'b0, a, 3'b000} : 12'b0;
	assign group_b_row0 = b[4] ? {4'b0000, a}       : 12'b0;
	assign group_b_row1 = b[5] ? {3'b000, a, 1'b0} : 12'b0;
	assign group_b_row2 = b[6] ? {2'b00, a, 2'b00} : 12'b0;
	assign group_b_row3 = b[7] ? {1'b0, a, 3'b000} : 12'b0;

	assign group_a_exact = group_a_row0 + group_a_row1 + group_a_row2 + group_a_row3;
	assign group_b_exact = group_b_row0 + group_b_row1 + group_b_row2 + group_b_row3;
	assign group_a_approx = {group_a_exact[11:2], 2'b00};
	assign group_b_approx = {group_b_exact[11:2], 2'b00};
	assign p = {group_b_approx, 4'b0000} + {4'b0000, group_a_approx};
endmodule

task3/group8/rtl/approx_mul16_loa.v
`timescale 1 ns / 1 ps

module approx_mul16_loa #(
	parameter integer LOA_K = 4,
	parameter [8*22-1:0] V2_IMPLEMENTATION = "PLACEHOLDER_EXACT"
) (
	input  [15:0] a,
	input  [15:0] b,
	output [31:0] p
);
	// 16x16 decomposition:
	// M0 = A[ 7:0] * B[ 7:0]
	// M1 = A[ 7:0] * B[15:8]
	// M2 = A[15:8] * B[ 7:0]
	// M3 = A[15:8] * B[15:8]
	//
	// Accumulation uses the low byte of M0 exactly and applies the LOA only to
	// the overlapping upper slice [31:8]:
	//   upper0 = M0[15:8]
	//   upper1 = M1
	//   upper2 = M2
	//   upper3 = (M3 << 8)
	//   upper_sum = LOA(LOA(upper0, upper1), LOA(upper2, upper3))
	//   P = {upper_sum, M0[7:0]}
	//
	// This mapping preserves the standard 8x8 decomposition while ensuring that
	// k = 4 or 6 actually approximates overlapping accumulation bits.

	wire [15:0] m0;
	wire [15:0] m1;
	wire [15:0] m2;
	wire [15:0] m3;

	wire [23:0] upper0;
	wire [23:0] upper1;
	wire [23:0] upper2;
	wire [23:0] upper3;

	wire [23:0] stage0_sum;
	wire [23:0] stage1_sum;
	wire [23:0] stage2_sum;
	wire        unused_carry0;
	wire        unused_carry1;
	wire        unused_carry2;

	v2_8x8_multiplier #(
		.V2_IMPLEMENTATION(V2_IMPLEMENTATION)
	) u_m0 (
		.a(a[7:0]),
		.b(b[7:0]),
		.p(m0)
	);

	v2_8x8_multiplier #(
		.V2_IMPLEMENTATION(V2_IMPLEMENTATION)
	) u_m1 (
		.a(a[7:0]),
		.b(b[15:8]),
		.p(m1)
	);

	v2_8x8_multiplier #(
		.V2_IMPLEMENTATION(V2_IMPLEMENTATION)
	) u_m2 (
		.a(a[15:8]),
		.b(b[7:0]),
		.p(m2)
	);

	v2_8x8_multiplier #(
		.V2_IMPLEMENTATION(V2_IMPLEMENTATION)
	) u_m3 (
		.a(a[15:8]),
		.b(b[15:8]),
		.p(m3)
	);

	assign upper0 = {16'b0, m0[15:8]};
	assign upper1 = {8'b0, m1};
	assign upper2 = {8'b0, m2};
	assign upper3 = {m3, 8'b0};

	loa_adder #(
		.WIDTH(24),
		.K(LOA_K)
	) u_add0 (
		.a(upper0),
		.b(upper1),
		.sum(stage0_sum),
		.carry_out(unused_carry0)
	);

	loa_adder #(
		.WIDTH(24),
		.K(LOA_K)
	) u_add1 (
		.a(upper2),
		.b(upper3),
		.sum(stage1_sum),
		.carry_out(unused_carry1)
	);

	loa_adder #(
		.WIDTH(24),
		.K(LOA_K)
	) u_add2 (
		.a(stage0_sum),
		.b(stage1_sum),
		.sum(stage2_sum),
		.carry_out(unused_carry2)
	);

	assign p = {stage2_sum, m0[7:0]};
endmodule

group8/tb/approx_mul16_loa_tb.v
`timescale 1 ns / 1 ps

module approx_mul16_loa_tb;
	parameter integer LOA_K = 4;

	reg  [15:0] a;
	reg  [15:0] b;
	wire [31:0] p;

	integer idx;
	integer errors;
	integer seed;
	reg [1023:0] vcd_file;
	reg [31:0] expected;
	reg [31:0] exact_product;

	approx_mul16_loa #(
		.LOA_K(LOA_K)
	) dut (
		.a(a),
		.b(b),
		.p(p)
	);

	function [15:0] v2_mul8_model;
		input [7:0] x;
		input [7:0] y;
		reg [11:0] group_a_exact;
		reg [11:0] group_b_exact;
		begin
			group_a_exact = x * y[3:0];
			group_b_exact = x * y[7:4];
			v2_mul8_model = {group_b_exact[11:2], 2'b00, 4'b0000} + {4'b0000, group_a_exact[11:2], 2'b00};
		end
	endfunction

	function [31:0] loa_sum_model;
		input [31:0] x;
		input [31:0] y;
		reg [31:0] tmp;
		reg carry;
		reg [32-LOA_K:0] upper;
		integer i;
		begin
			tmp = 32'b0;
			for (i = 0; i < LOA_K; i = i + 1)
				tmp[i] = x[i] | y[i];
			carry = x[LOA_K-1] & y[LOA_K-1];
			upper = {1'b0, x[31:LOA_K]} + {1'b0, y[31:LOA_K]} + carry;
			tmp[31:LOA_K] = upper[31-LOA_K:0];
			loa_sum_model = tmp;
		end
	endfunction

	function [23:0] loa_sum24_model;
		input [23:0] x;
		input [23:0] y;
		reg [23:0] tmp;
		reg carry;
		reg [24-LOA_K:0] upper;
		integer i;
		begin
			tmp = 24'b0;
			for (i = 0; i < LOA_K; i = i + 1)
				tmp[i] = x[i] | y[i];
			carry = x[LOA_K-1] & y[LOA_K-1];
			upper = {1'b0, x[23:LOA_K]} + {1'b0, y[23:LOA_K]} + carry;
			tmp[23:LOA_K] = upper[23-LOA_K:0];
			loa_sum24_model = tmp;
		end
	endfunction

	function [31:0] approx_mul16_model;
		input [15:0] x;
		input [15:0] y;
		reg [15:0] m0;
		reg [15:0] m1;
		reg [15:0] m2;
		reg [15:0] m3;
		reg [23:0] u0;
		reg [23:0] u1;
		reg [23:0] u2;
		reg [23:0] u3;
		reg [23:0] s0;
		reg [23:0] s1;
		reg [23:0] s2;
		begin
			m0 = v2_mul8_model(x[7:0], y[7:0]);
			m1 = v2_mul8_model(x[7:0], y[15:8]);
			m2 = v2_mul8_model(x[15:8], y[7:0]);
			m3 = v2_mul8_model(x[15:8], y[15:8]);
			u0 = {16'b0, m0[15:8]};
			u1 = {8'b0, m1};
			u2 = {8'b0, m2};
			u3 = {m3, 8'b0};
			s0 = loa_sum24_model(u0, u1);
			s1 = loa_sum24_model(u2, u3);
			s2 = loa_sum24_model(s0, s1);
			approx_mul16_model = {s2, m0[7:0]};
		end
	endfunction

	task run_case;
		input [15:0] in_a;
		input [15:0] in_b;
		begin
			a = in_a;
			b = in_b;
			#1;
			expected = approx_mul16_model(in_a, in_b);
			exact_product = in_a * in_b;
			if (p !== expected) begin
				errors = errors + 1;
				$display("FAIL k=%0d a=0x%04x b=0x%04x dut=0x%08x exp=0x%08x exact=0x%08x",
					LOA_K, in_a, in_b, p, expected, exact_product);
			end else begin
				$display("PASS k=%0d a=0x%04x b=0x%04x approx=0x%08x exact=0x%08x",
					LOA_K, in_a, in_b, p, exact_product);
			end
		end
	endtask

	initial begin
		errors = 0;
		seed = 32'h1badc0de;

		if ($value$plusargs("vcd=%s", vcd_file)) begin
			$dumpfile(vcd_file);
			$dumpvars(0, approx_mul16_loa_tb);
		end

		run_case(16'h0000, 16'h0000);
		run_case(16'h0001, 16'h0001);
		run_case(16'h000f, 16'h0003);
		run_case(16'h00ff, 16'h0002);
		run_case(16'h00ff, 16'h00ff);
		run_case(16'h1234, 16'h5678);
		run_case(16'ha5a5, 16'h5a5a);
		run_case(16'hffff, 16'h0001);
		run_case(16'hffff, 16'hffff);
		run_case(16'h8000, 16'h0002);

		for (idx = 0; idx < 50; idx = idx + 1) begin
			run_case($random(seed), $random(seed));
		end

		if (errors != 0) begin
			$display("TEST FAILED with %0d mismatches", errors);
			$finish(1);
		end

		$display("TEST PASSED for LOA_K=%0d", LOA_K);
		$finish;
	end
endmodule

build/sim/approx_mul16_loa_tb_k4.vcd
$date
	Sat Mar 28 16:10:17 2026
$end
$version
	Icarus Verilog
$end
$timescale
	1ps
$end
$scope module approx_mul16_loa_tb $end
$var wire 32 ! p [31:0] $end
$var parameter 32 " LOA_K $end
$var reg 16 # a [15:0] $end
$var reg 16 $ b [15:0] $end
$var reg 32 % exact_product [31:0] $end
$var reg 32 & expected [31:0] $end
$var reg 1024 ' vcd_file [1023:0] $end
$var integer 32 ( errors [31:0] $end
$var integer 32 ) idx [31:0] $end
$var integer 32 * seed [31:0] $end
$scope function approx_mul16_model $end
$var reg 16 + m0 [15:0] $end
$var reg 16 , m1 [15:0] $end
$var reg 16 - m2 [15:0] $end
$var reg 16 . m3 [15:0] $end
$var reg 24 / s0 [23:0] $end
$var reg 24 0 s1 [23:0] $end
$var reg 24 1 s2 [23:0] $end
$var reg 24 2 u0 [23:0] $end
$var reg 24 3 u1 [23:0] $end
$var reg 24 4 u2 [23:0] $end
$var reg 24 5 u3 [23:0] $end
$var reg 16 6 x [15:0] $end
$var reg 16 7 y [15:0] $end
$upscope $end
$scope function loa_sum24_model $end
$var reg 1 8 carry $end
$var reg 24 9 tmp [23:0] $end
$var reg 21 : upper [20:0] $end
$var reg 24 ; x [23:0] $end
$var reg 24 < y [23:0] $end
$var integer 32 = i [31:0] $end
$upscope $end
$scope function loa_sum_model $end
$var reg 1 > carry $end
$var reg 32 ? tmp [31:0] $end
$var reg 29 @ upper [28:0] $end
$var reg 32 A x [31:0] $end
$var reg 32 B y [31:0] $end
$var integer 32 C i [31:0] $end
$upscope $end
$scope function v2_mul8_model $end
$var reg 12 D group_a_exact [11:0] $end
$var reg 12 E group_b_exact [11:0] $end
$var reg 8 F x [7:0] $end
$var reg 8 G y [7:0] $end
$upscope $end
$scope module dut $end
$var wire 16 H a [15:0] $end
$var wire 16 I b [15:0] $end
$var wire 24 J upper3 [23:0] $end
$var wire 24 K upper2 [23:0] $end
$var wire 24 L upper1 [23:0] $end
$var wire 24 M upper0 [23:0] $end
$var wire 1 N unused_carry2 $end
$var wire 1 O unused_carry1 $end
$var wire 1 P unused_carry0 $end
$var wire 24 Q stage2_sum [23:0] $end
$var wire 24 R stage1_sum [23:0] $end
$var wire 24 S stage0_sum [23:0] $end
$var wire 32 T p [31:0] $end
$var wire 16 U m3 [15:0] $end
$var wire 16 V m2 [15:0] $end
$var wire 16 W m1 [15:0] $end
$var wire 16 X m0 [15:0] $end
$var parameter 32 Y LOA_K $end
$var parameter 176 Z V2_IMPLEMENTATION $end
$scope module u_add0 $end
$var wire 24 [ a [23:0] $end
$var wire 24 \ b [23:0] $end
$var wire 1 ] lower_carry $end
$var wire 4 ^ lower_sum [3:0] $end
$var wire 21 _ upper_sum_ext [20:0] $end
$var wire 24 ` sum [23:0] $end
$var wire 1 P carry_out $end
$var parameter 32 a K $end
$var parameter 32 b WIDTH $end
$upscope $end
$scope module u_add1 $end
$var wire 24 c a [23:0] $end
$var wire 24 d b [23:0] $end
$var wire 1 e lower_carry $end
$var wire 4 f lower_sum [3:0] $end
$var wire 21 g upper_sum_ext [20:0] $end
$var wire 24 h sum [23:0] $end
$var wire 1 O carry_out $end
$var parameter 32 i K $end
$var parameter 32 j WIDTH $end
$upscope $end
$scope module u_add2 $end
$var wire 24 k a [23:0] $end
$var wire 24 l b [23:0] $end
$var wire 1 m lower_carry $end
$var wire 4 n lower_sum [3:0] $end
$var wire 21 o upper_sum_ext [20:0] $end
$var wire 24 p sum [23:0] $end
$var wire 1 N carry_out $end
$var parameter 32 q K $end
$var parameter 32 r WIDTH $end
$upscope $end
$scope module u_m0 $end
$var wire 8 s a [7:0] $end
$var wire 8 t b [7:0] $end
$var wire 16 u p [15:0] $end
$var wire 12 v group_b_exact [11:0] $end
$var wire 12 w group_b_approx [11:0] $end
$var wire 12 x group_a_exact [11:0] $end
$var wire 12 y group_a_approx [11:0] $end
$var parameter 176 z V2_IMPLEMENTATION $end
$upscope $end
$scope module u_m1 $end
$var wire 8 { a [7:0] $end
$var wire 8 | b [7:0] $end
$var wire 16 } p [15:0] $end
$var wire 12 ~ group_b_exact [11:0] $end
$var wire 12 !" group_b_approx [11:0] $end
$var wire 12 "" group_a_exact [11:0] $end
$var wire 12 #" group_a_approx [11:0] $end
$var parameter 176 $" V2_IMPLEMENTATION $end
$upscope $end
$scope module u_m2 $end
$var wire 8 %" a [7:0] $end
$var wire 8 &" b [7:0] $end
$var wire 16 '" p [15:0] $end
$var wire 12 (" group_b_exact [11:0] $end
$var wire 12 )" group_b_approx [11:0] $end
$var wire 12 *" group_a_exact [11:0] $end
$var wire 12 +" group_a_approx [11:0] $end
$var parameter 176 ," V2_IMPLEMENTATION $end
$upscope $end
$scope module u_m3 $end
$var wire 8 -" a [7:0] $end
$var wire 8 ." b [7:0] $end
$var wire 16 /" p [15:0] $end
$var wire 12 0" group_b_exact [11:0] $end
$var wire 12 1" group_b_approx [11:0] $end
$var wire 12 2" group_a_exact [11:0] $end
$var wire 12 3" group_a_approx [11:0] $end
$var parameter 176 4" V2_IMPLEMENTATION $end
$upscope $end
$upscope $end
$scope task run_case $end
$var reg 16 5" in_a [15:0] $end
$var reg 16 6" in_b [15:0] $end
$upscope $end
$upscope $end
$enddefinitions $end
$comment Show the parameter values. $end
$dumpall
b101000001001100010000010100001101000101010010000100111101001100010001000100010101010010010111110100010101011000010000010100001101010100 4"
b101000001001100010000010100001101000101010010000100111101001100010001000100010101010010010111110100010101011000010000010100001101010100 ,"
b101000001001100010000010100001101000101010010000100111101001100010001000100010101010010010111110100010101011000010000010100001101010100 $"
b101000001001100010000010100001101000101010010000100111101001100010001000100010101010010010111110100010101011000010000010100001101010100 z
b11000 r
b100 q
b11000 j
b100 i
b11000 b
b100 a
b101000001001100010000010100001101000101010010000100111101001100010001000100010101010010010111110100010101011000010000010100001101010100 Z
b100 Y
b100 "
$end
#0
$dumpvars
b0 6"
b0 5"
b0 3"
b0 2"
b0 1"
b0 0"
b0 /"
b0 ."
b0 -"
b0 +"
b0 *"
b0 )"
b0 ("
b0 '"
b0 &"
b0 %"
b0 #"
b0 ""
b0 !"
b0 ~
b0 }
b0 |
b0 {
b0 y
b0 x
b0 w
b0 v
b0 u
b0 t
b0 s
b0 p
b0 o
b0 n
0m
b0 l
b0 k
b0 h
b0 g
b0 f
0e
b0 d
b0 c
b0 `
b0 _
b0 ^
0]
b0 \
b0 [
b0 X
b0 W
b0 V
b0 U
b0 T
b0 S
b0 R
b0 Q
0P
0O
0N
b0 M
b0 L
b0 K
b0 J
b0 I
b0 H
bx G
bx F
bx E
bx D
bx C
bx B
bx A
bx @
bx ?
x>
bx =
bx <
bx ;
bx :
bx 9
x8
bx 7
bx 6
bx 5
bx 4
bx 3
bx 2
bx 1
bx 0
bx /
bx .
bx -
bx ,
bx +
b11011101011011100000011011110 *
bx )
b0 (
b11000100111010101101001011011000110010000101111011100110110100101101101001011110110000101110000011100000111001001101111011110000101111101101101011101010110110000110001001101100101111101101100011011110110000101011111011101000110001001011111011010110011010000101110011101100110001101100100 '
bx &
bx %
b0 $
b0 #
b0 !
$end
#1000
b1 x
b1 t
b1 &"
b1 s
b1 {
b1 $
b1 I
b1 #
b1 H
b1 6"
b1 5"
b0 %
b0 &
b0 1
b0 0
b0 /
b0 :
08
b100 =
b0 9
b0 ;
b0 <
b0 5
b0 4
b0 3
b0 2
b0 .
b0 -
b0 ,
b0 +
b0 E
b0 D
b0 F
b0 G
b0 6
b0 7
#2000
b101100 !
b101100 T
b101100 X
b101100 u
b101100 y
b101101 x
b11 t
b11 &"
b1111 s
b1111 {
b11 $
b11 I
b1111 #
b1111 H
b11 6"
b1111 5"
b1 %
b100 =
b0 D
b0 F
b0 G
b1 6
b1 7
#3000
b1 Q
b1 p
b1 n
b1 S
b1 `
b1 k
b1 ^
b111111100 !
b111111100 T
b1 M
b1 [
b111111100 X
b111111100 u
b111111100 y
b111111110 x
b10 t
b10 &"
b11111111 s
b11111111 {
b10 $
b10 I
b11111111 #
b11111111 H
b10 6"
b11111111 5"
b101101 %
b101100 &
b100 =
b101100 +
b0 D
b0 F
b0 G
b1111 6
b11 7
#4000
b11101 Q
b11101 p
b1101 n
b1 o
b11101 S
b11101 `
b11101 k
b1101 ^
b1 _
b1110111100000 !
b1110111100000 T
b11101 M
b11101 [
b1110111100000 X
b1110111100000 u
b111011110000 y
b111011110000 w
b111011110001 x
b111011110001 v
b11111111 t
b11111111 &"
b11111111 $
b11111111 I
b11111111 6"
b111111110 %
b111111100 &
b1 1
b1 /
b1 9
b100 =
b1 ;
b1 2
b111111100 +
b0 D
b0 F
b0 G
b11111111 6
b10 7
#5000
b1100011101001111 Q
b1100011101001111 p
b1111 n
1m
b110001110100 o
b1000111111 S
b1000111111 `
b1000111111 k
b1111 ^
b100011 _
b1100010100001100 R
b1100010100001100 h
b1100010100001100 l
b1100 f
b110001010000 g
b1000111100 L
b1000111100 \
b1100010000000000 J
b1100010000000000 d
b110001110100111100001100 !
b110001110100111100001100 T
b11 M
b11 [
b1000111100 W
b1000111100 }
b11000100 U
b11000100 /"
b100001100 K
b100001100 c
b100111000 #"
b100000100 !"
b1101100 3"
b1011000 1"
b1100001100 X
b1100001100 u
b100001100 V
b100001100 '"
b110100000 y
b101101100 w
b10010000 +"
b1111100 )"
b100111000 ""
b100000100 ~
b1101100 2"
b1011010 0"
b110100000 x
b101101100 v
b10010000 *"
b1111110 ("
b1111000 t
b1010110 |
b1111000 &"
b1010110 ."
b110100 s
b110100 {
b10010 %"
b10010 -"
b101011001111000 $
b101011001111000 I
b1001000110100 #
b1001000110100 H
b101011001111000 6"
b1001000110100 5"
b1111111000000001 %
b1110111100000 &
b11101 1
b11101 /
b1 :
b100 =
b11101 9
b11101 ;
b11101 2
b1110111100000 +
b0 E
b0 D
b0 F
b0 G
b11111111 7
#6000
b10011011101101101001 Q
b10011011101101101001 p
b1001 n
1m
b1001101110110110 o
1]
b100110111001 S
b100110111001 `
b100110111001 k
b10011011000110101000 R
b10011011000110101000 h
b10011011000110101000 l
b1001 ^
b10011011 _
b1000 f
b1001101100011010 g
b1001101110110110100110101000 !
b1001101110110110100110101000 T
b1001 M
b1001 [
b100110101000 L
b100110101000 \
b100110101000 K
b100110101000 c
b10011010100000000000 J
b10011010100000000000 d
b100110101000 X
b100110101000 u
b100110101000 W
b100110101000 }
b100110101000 V
b100110101000 '"
b100110101000 U
b100110101000 /"
b11001110000 y
b1100111000 w
b11001110000 #"
b1100111000 !"
b11001110000 +"
b1100111000 )"
b11001110000 3"
b1100111000 1"
b11001110010 x
b1100111001 v
b11001110010 ""
b1100111001 ~
b11001110010 *"
b1100111001 ("
b11001110010 2"
b1100111001 0"
b1011010 t
b1011010 |
b1011010 &"
b1011010 ."
b10100101 s
b10100101 {
b10100101 %"
b10100101 -"
b101101001011010 $
b101101001011010 I
b1010010110100101 #
b1010010110100101 H
b101101001011010 6"
b1010010110100101 5"
b110001001100000000001100000 %
b110001110100111100001100 &
b1100011101001111 1
18
b1100010100001100 0
b1000111111 /
b110001110100 :
b100 =
b1100011101001111 9
b1000111111 ;
b1100010100001100 <
b1100010000000000 5
b100001100 4
b1000111100 3
b11 2
b11000100 .
b100001100 -
b1000111100 ,
b1100001100 +
b1011010 E
b1101100 D
b10010 F
b1010110 G
b1001000110100 6
b101011001111000 7
#7000
0m
b11111100 Q
b11111100 p
b1100 n
b1111 o
0]
b0 S
b0 `
b0 k
b11111100 R
b11111100 h
b11111100 l
b0 ^
b0 _
b1100 f
b1111 g
b1111110011111100 !
b1111110011111100 T
b0 M
b0 [
b0 L
b0 \
b11111100 K
b11111100 c
b0 J
b0 d
b11111100 X
b11111100 u
b0 W
b0 }
b11111100 V
b11111100 '"
b0 U
b0 /"
b11111100 y
b0 w
b0 #"
b0 !"
b11111100 +"
b0 )"
b0 3"
b0 1"
b11111111 x
b0 v
b0 ""
b0 ~
b11111111 *"
b0 ("
b0 2"
b0 0"
b1 t
b0 |
b1 &"
b0 ."
b11111111 s
b11111111 {
b11111111 %"
b11111111 -"
b1 $
b1 I
b1111111111111111 #
b1111111111111111 H
b1 6"
b1111111111111111 5"
b111010011101100011111000000010 %
b1001101110110110100110101000 &
b10011011101101101001 1
b10011011000110101000 0
18
b100110111001 /
b1001101110110110 :
b100 =
b10011011101101101001 9
b100110111001 ;
b10011011000110101000 <
b10011010100000000000 5
b100110101000 4
b100110101000 3
b1001 2
b100110101000 .
b100110101000 -
b100110101000 ,
b100110101000 +
b1100111001 E
b11001110010 D
b10100101 F
b1011010 G
b1010010110100101 6
b101101001011010 7
#8000
b111100001101111011101 Q
b111100001101111011101 p
b1101 n
b11110000110111101 o
b1110111111101 S
b1110111111101 `
b1110111111101 k
b1101 ^
b111011111110111100000 R
b111011111110111100000 h
b111011111110111100000 l
b111011111 _
b0 f
b11101111111011110 g
b11110000110111101110111100000 !
b11110000110111101110111100000 T
b11101 M
b11101 [
b1110111100000 L
b1110111100000 \
b1110111100000 K
b1110111100000 c
b111011110000000000000 J
b111011110000000000000 d
b1110111100000 X
b1110111100000 u
b1110111100000 W
b1110111100000 }
b1110111100000 V
b1110111100000 '"
b1110111100000 U
b1110111100000 /"
b111011110000 y
b111011110000 w
b111011110000 #"
b111011110000 !"
b111011110000 +"
b111011110000 )"
b111011110000 3"
b111011110000 1"
b111011110001 x
b111011110001 v
b111011110001 ""
b111011110001 ~
b111011110001 *"
b111011110001 ("
b111011110001 2"
b111011110001 0"
b11111111 t
b11111111 |
b11111111 &"
b11111111 ."
b1111111111111111 $
b1111111111111111 I
b1111111111111111 6"
b1111111111111111 %
b1111110011111100 &
b11111100 1
b11111100 0
b0 /
b1111 :
08
b100 =
b11111100 9
b0 ;
b11111100 <
b0 5
b11111100 4
b0 3
b0 2
b0 .
b11111100 -
b0 ,
b11111100 +
b0 E
b0 D
b11111111 F
b0 G
b1111111111111111 6
b1 7
#9000
b100000000 Q
b100000000 p
b0 n
b10000 o
b0 S
b0 `
b0 k
b100000000 R
b100000000 h
b100000000 l
b0 ^
b0 _
b10000 g
b10000000000000000 !
b10000000000000000 T
b0 M
b0 [
b0 L
b0 \
b100000000 K
b100000000 c
b0 J
b0 d
b0 X
b0 u
b0 W
b0 }
b100000000 V
b100000000 '"
b0 U
b0 /"
b0 y
b0 w
b0 #"
b0 !"
b100000000 +"
b0 )"
b0 3"
b0 1"
b0 x
b0 v
b0 ""
b0 ~
b100000000 *"
b0 ("
b0 2"
b0 0"
b10 t
b0 |
b10 &"
b0 ."
b0 s
b0 {
b10000000 %"
b10000000 -"
b10 $
b10 I
b1000000000000000 #
b1000000000000000 H
b10 6"
b1000000000000000 5"
b11111111111111100000000000000001 %
b11110000110111101110111100000 &
b111100001101111011101 1
b111011111110111100000 0
b1110111111101 /
b11110000110111101 :
b100 =
b111100001101111011101 9
b1110111111101 ;
b111011111110111100000 <
b111011110000000000000 5
b1110111100000 4
b1110111100000 3
b11101 2
b1110111100000 .
b1110111100000 -
b1110111100000 ,
b1110111100000 +
b111011110001 E
b111011110001 D
b11111111 G
b1111111111111111 7
#10000
b1110100000111011111 Q
b1110100000111011111 p
b1111 n
1m
b111010000011101 o
b10011001111 S
b10011001111 `
b10011001111 k
b1110011110100001100 R
b1110011110100001100 h
b1110011110100001100 l
b1111 ^
b1001100 _
b1100 f
b11 M
b11 [
b111001111010000 g
b10011001100 L
b10011001100 \
b1110011100000000000 J
b1110011100000000000 d
b111010000011101111101011100 !
b111010000011101111101011100 T
b10011001100 W
b10011001100 }
b11100111000 U
b11100111000 /"
b10100001100 K
b10100001100 c
b101110000 w
b1011100000 #"
b111101100 !"
b1000101000 )"
b10001010100 3"
b1011100100 1"
b1101011100 X
b1101011100 u
b10100001100 V
b10100001100 '"
b111101100 y
b1011100100 +"
b101110001 v
b1011100010 ""
b111101100 ~
b1000101011 ("
b10001010110 2"
b1011100100 0"
b111101100 x
b1011100100 *"
b110100 t
b1000110 |
b110100 &"
b1000110 ."
b1111011 s
b1111011 {
b10111001 %"
b10111001 -"
b100011000110100 $
b100011000110100 I
b1011100101111011 #
b1011100101111011 H
b100011000110100 6"
b1011100101111011 5"
b11010000010110100010101011100 *
b0 )
b10000000000000000 %
b10000000000000000 &
b100000000 1
b100000000 0
b0 /
b10000 :
b100 =
b100000000 9
b0 ;
b100000000 <
b0 5
b100000000 4
b0 3
b0 2
b0 .
b100000000 -
b0 ,
b0 +
b0 E
b0 D
b10000000 F
b0 G
b1000000000000000 6
b10 7
#11000
b100111100001010111 Q
b100111100001010111 p
b111 n
0m
b10011110000101 o
b100111010000000000 R
b100111010000000000 h
b100111010000000000 l
b0 f
b10001010111 S
b10001010111 `
b10001010111 k
b111 ^
b1000101 _
b10011101000000 g
b111 M
b111 [
b10011110000101011100011000 !
b10011110000101011100011000 T
b10001010100 L
b10001010100 \
b10000000000 K
b10000000000 c
b100111000000000000 J
b100111000000000000 d
b11100011000 X
b11100011000 u
b10001010100 W
b10001010100 }
b10000000000 V
b10000000000 '"
b1001110000 U
b1001110000 /"
b1111110000 y
b1100101000 w
b11001000 #"
b1110001100 !"
b1000111000 +"
b111001000 )"
b1110000 3"
b1000000000 1"
b1111110010 x
b1100101000 v
b11001010 ""
b1110001101 ~
b1000111010 *"
b111001000 ("
b1110010 2"
b1000000001 0"
b10001010 t
b10010010 |
b10001010 &"
b10010010 ."
b1100101 s
b1100101 {
b111001 %"
b111001 -"
b1001001010001010 $
b1001001010001010 I
b11100101100101 #
b11100101100101 H
b1001001010001010 6"
b11100101100101 5"
b1000101011001111001000110001010 *
b1 )
b110010110111010100111011111100 %
b111010000011101111101011100 &
b1110100000111011111 1
18
b1110011110100001100 0
b10011001111 /
b111010000011101 :
b100 =
b1110100000111011111 9
b10011001111 ;
b1110011110100001100 <
b1110011100000000000 5
b10100001100 4
b10011001100 3
b11 2
b11100111000 .
b10100001100 -
b10011001100 ,
b1101011100 +
b1011100100 E
b10001010110 D
b10111001 F
b1000110 G
b1011100101111011 6
b100011000110100 7
#12000
1m
b11101000011110011111 Q
b11101000011110011111 p
b1111 n
b1110100001111001 o
b1010100001111 S
b1010100001111 `
b1010100001111 k
b1111 ^
b11100111001010001000 R
b11100111001010001000 h
b11100111001010001000 l
b101010000 _
b1000 f
b1110011100101000 g
b1110100001111001111101011100 !
b1110100001111001111101011100 T
b1111 M
b1111 [
b1010100000100 L
b1010100000100 \
b101010001000 K
b101010001000 c
b11100110100000000000 J
b11100110100000000000 d
b111101011100 X
b111101011100 u
b1010100000100 W
b1010100000100 }
b101010001000 V
b101010001000 '"
b111001101000 U
b111001101000 /"
b1100111100 y
b110000100000 w
b100011100100 #"
b110000100000 !"
b1000111000 +"
b100001010000 )"
b11000011000 3"
b100001010000 1"
b1100111100 x
b110000100001 v
b100011100101 ""
b110000100001 ~
b1000111000 *"
b100001010010 ("
b11000011010 2"
b100001010010 0"
b11110100 t
b11111011 |
b11110100 &"
b11111011 ."
b11001111 s
b11001111 {
b10001110 %"
b10001110 -"
b1111101111110100 $
b1111101111110100 I
b1000111011001111 #
b1000111011001111 H
b1111101111110100 6"
b1000111011001111 5"
b11111010000111001111100011101000 *
b10 )
b100000110110101000101001110010 %
b10011110000101011100011000 &
b100111100001010111 1
b100111010000000000 0
b10001010111 /
b10011110000101 :
08
b100 =
b100111100001010111 9
b10001010111 ;
b100111010000000000 <
b100111000000000000 5
b10000000000 4
b10001010100 3
b111 2
b1001110000 .
b10000000000 -
b10001010100 ,
b11100011000 +
b1000000001 E
b1110010 D
b111001 F
b10010010 G
b11100101100101 6
b1001001010001010 7
