task3/group8/rtl/loa_adder.v
`timescale 1 ns / 1 ps

module loa_adder #(
	parameter integer WIDTH = 32,
	parameter integer K = 4
) (
	input  [WIDTH-1:0] a,
	input  [WIDTH-1:0] b,
	output [WIDTH-1:0] sum,
	output             carry_out
);
	initial begin
		if (K <= 0 || K >= WIDTH) begin
			$display("ERROR: loa_adder requires 0 < K < WIDTH. WIDTH=%0d K=%0d", WIDTH, K);
			$finish;
		end
	end

	wire [K-1:0] lower_sum;
	wire         lower_carry;
	wire [WIDTH-K:0] upper_sum_ext;

	assign lower_sum = a[K-1:0] | b[K-1:0];
	assign lower_carry = a[K-1] & b[K-1];
	assign upper_sum_ext = {1'b0, a[WIDTH-1:K]} + {1'b0, b[WIDTH-1:K]} + lower_carry;

	assign sum[K-1:0] = lower_sum;
	assign sum[WIDTH-1:K] = upper_sum_ext[WIDTH-K-1:0];
	assign carry_out = upper_sum_ext[WIDTH-K];
endmodule

group8/rtl/v2_8x8_multiplier.v
`timescale 1 ns / 1 ps

module v2_8x8_multiplier #(
	parameter [8*22-1:0] V2_IMPLEMENTATION = "BEST_EFFORT_22"
) (
	input  [7:0] a,
	input  [7:0] b,
	output [15:0] p
);
	// Best-effort Group-8 construction for the 22 block:
	// - split the 8x8 multiplication into two 8x4 groups using b[3:0] and b[7:4]
	// - approximate each group by clearing its two least-significant local bits
	// - accumulate the two groups in the standard shifted form
	//
	// This matches the available information that the 22 architecture uses two
	// approximated positions in each of the lower-order and higher-order groups.
	// Replace this model with the exact course-provided 22/V2 cell placement if a
	// precise block diagram becomes available.
	wire [11:0] group_a_exact;
	wire [11:0] group_b_exact;
	wire [11:0] group_a_approx;
	wire [11:0] group_b_approx;
	wire [11:0] group_a_row0;
	wire [11:0] group_a_row1;
	wire [11:0] group_a_row2;
	wire [11:0] group_a_row3;
	wire [11:0] group_b_row0;
	wire [11:0] group_b_row1;
	wire [11:0] group_b_row2;
	wire [11:0] group_b_row3;

	assign group_a_row0 = b[0] ? {4'b0000, a}       : 12'b0;
	assign group_a_row1 = b[1] ? {3'b000, a, 1'b0} : 12'b0;
	assign group_a_row2 = b[2] ? {2'b00, a, 2'b00} : 12'b0;
	assign group_a_row3 = b[3] ? {1'b0, a, 3'b000} : 12'b0;
	assign group_b_row0 = b[4] ? {4'b0000, a}       : 12'b0;
	assign group_b_row1 = b[5] ? {3'b000, a, 1'b0} : 12'b0;
	assign group_b_row2 = b[6] ? {2'b00, a, 2'b00} : 12'b0;
	assign group_b_row3 = b[7] ? {1'b0, a, 3'b000} : 12'b0;

	assign group_a_exact = group_a_row0 + group_a_row1 + group_a_row2 + group_a_row3;
	assign group_b_exact = group_b_row0 + group_b_row1 + group_b_row2 + group_b_row3;
	assign group_a_approx = {group_a_exact[11:2], 2'b00};
	assign group_b_approx = {group_b_exact[11:2], 2'b00};
	assign p = {group_b_approx, 4'b0000} + {4'b0000, group_a_approx};
endmodule

task3/group8/rtl/approx_mul16_loa.v
`timescale 1 ns / 1 ps

module approx_mul16_loa #(
	parameter integer LOA_K = 4,
	parameter [8*22-1:0] V2_IMPLEMENTATION = "PLACEHOLDER_EXACT"
) (
	input  [15:0] a,
	input  [15:0] b,
	output [31:0] p
);
	// 16x16 decomposition:
	// M0 = A[ 7:0] * B[ 7:0]
	// M1 = A[ 7:0] * B[15:8]
	// M2 = A[15:8] * B[ 7:0]
	// M3 = A[15:8] * B[15:8]
	//
	// Accumulation uses the low byte of M0 exactly and applies the LOA only to
	// the overlapping upper slice [31:8]:
	//   upper0 = M0[15:8]
	//   upper1 = M1
	//   upper2 = M2
	//   upper3 = (M3 << 8)
	//   upper_sum = LOA(LOA(upper0, upper1), LOA(upper2, upper3))
	//   P = {upper_sum, M0[7:0]}
	//
	// This mapping preserves the standard 8x8 decomposition while ensuring that
	// k = 4 or 6 actually approximates overlapping accumulation bits.

	wire [15:0] m0;
	wire [15:0] m1;
	wire [15:0] m2;
	wire [15:0] m3;

	wire [23:0] upper0;
	wire [23:0] upper1;
	wire [23:0] upper2;
	wire [23:0] upper3;

	wire [23:0] stage0_sum;
	wire [23:0] stage1_sum;
	wire [23:0] stage2_sum;
	wire        unused_carry0;
	wire        unused_carry1;
	wire        unused_carry2;

	v2_8x8_multiplier #(
		.V2_IMPLEMENTATION(V2_IMPLEMENTATION)
	) u_m0 (
		.a(a[7:0]),
		.b(b[7:0]),
		.p(m0)
	);

	v2_8x8_multiplier #(
		.V2_IMPLEMENTATION(V2_IMPLEMENTATION)
	) u_m1 (
		.a(a[7:0]),
		.b(b[15:8]),
		.p(m1)
	);

	v2_8x8_multiplier #(
		.V2_IMPLEMENTATION(V2_IMPLEMENTATION)
	) u_m2 (
		.a(a[15:8]),
		.b(b[7:0]),
		.p(m2)
	);

	v2_8x8_multiplier #(
		.V2_IMPLEMENTATION(V2_IMPLEMENTATION)
	) u_m3 (
		.a(a[15:8]),
		.b(b[15:8]),
		.p(m3)
	);

	assign upper0 = {16'b0, m0[15:8]};
	assign upper1 = {8'b0, m1};
	assign upper2 = {8'b0, m2};
	assign upper3 = {m3, 8'b0};

	loa_adder #(
		.WIDTH(24),
		.K(LOA_K)
	) u_add0 (
		.a(upper0),
		.b(upper1),
		.sum(stage0_sum),
		.carry_out(unused_carry0)
	);

	loa_adder #(
		.WIDTH(24),
		.K(LOA_K)
	) u_add1 (
		.a(upper2),
		.b(upper3),
		.sum(stage1_sum),
		.carry_out(unused_carry1)
	);

	loa_adder #(
		.WIDTH(24),
		.K(LOA_K)
	) u_add2 (
		.a(stage0_sum),
		.b(stage1_sum),
		.sum(stage2_sum),
		.carry_out(unused_carry2)
	);

	assign p = {stage2_sum, m0[7:0]};
endmodule

group8/tb/approx_mul16_loa_tb.v
`timescale 1 ns / 1 ps

module approx_mul16_loa_tb;
	parameter integer LOA_K = 4;

	reg  [15:0] a;
	reg  [15:0] b;
	wire [31:0] p;

	integer idx;
	integer errors;
	integer seed;
	reg [1023:0] vcd_file;
	reg [31:0] expected;
	reg [31:0] exact_product;

	approx_mul16_loa #(
		.LOA_K(LOA_K)
	) dut (
		.a(a),
		.b(b),
		.p(p)
	);

	function [15:0] v2_mul8_model;
		input [7:0] x;
		input [7:0] y;
		begin
			// Placeholder model until the true V2 block is available.
			v2_mul8_model = x * y;
		end
	endfunction

	function [31:0] loa_sum_model;
		input [31:0] x;
		input [31:0] y;
		reg [31:0] tmp;
		reg carry;
		reg [32-LOA_K:0] upper;
		integer i;
		begin
			tmp = 32'b0;
			for (i = 0; i < LOA_K; i = i + 1)
				tmp[i] = x[i] | y[i];
			carry = x[LOA_K-1] & y[LOA_K-1];
			upper = {1'b0, x[31:LOA_K]} + {1'b0, y[31:LOA_K]} + carry;
			tmp[31:LOA_K] = upper[31-LOA_K:0];
			loa_sum_model = tmp;
		end
	endfunction

	function [23:0] loa_sum24_model;
		input [23:0] x;
		input [23:0] y;
		reg [23:0] tmp;
		reg carry;
		reg [24-LOA_K:0] upper;
		integer i;
		begin
			tmp = 24'b0;
			for (i = 0; i < LOA_K; i = i + 1)
				tmp[i] = x[i] | y[i];
			carry = x[LOA_K-1] & y[LOA_K-1];
			upper = {1'b0, x[23:LOA_K]} + {1'b0, y[23:LOA_K]} + carry;
			tmp[23:LOA_K] = upper[23-LOA_K:0];
			loa_sum24_model = tmp;
		end
	endfunction

	function [31:0] approx_mul16_model;
		input [15:0] x;
		input [15:0] y;
		reg [15:0] m0;
		reg [15:0] m1;
		reg [15:0] m2;
		reg [15:0] m3;
		reg [23:0] u0;
		reg [23:0] u1;
		reg [23:0] u2;
		reg [23:0] u3;
		reg [23:0] s0;
		reg [23:0] s1;
		reg [23:0] s2;
		begin
			m0 = v2_mul8_model(x[7:0], y[7:0]);
			m1 = v2_mul8_model(x[7:0], y[15:8]);
			m2 = v2_mul8_model(x[15:8], y[7:0]);
			m3 = v2_mul8_model(x[15:8], y[15:8]);
			u0 = {16'b0, m0[15:8]};
			u1 = {8'b0, m1};
			u2 = {8'b0, m2};
			u3 = {m3, 8'b0};
			s0 = loa_sum24_model(u0, u1);
			s1 = loa_sum24_model(u2, u3);
			s2 = loa_sum24_model(s0, s1);
			approx_mul16_model = {s2, m0[7:0]};
		end
	endfunction

	task run_case;
		input [15:0] in_a;
		input [15:0] in_b;
		begin
			a = in_a;
			b = in_b;
			#1;
			expected = approx_mul16_model(in_a, in_b);
			exact_product = in_a * in_b;
			if (p !== expected) begin
				errors = errors + 1;
				$display("FAIL k=%0d a=0x%04x b=0x%04x dut=0x%08x exp=0x%08x exact=0x%08x",
					LOA_K, in_a, in_b, p, expected, exact_product);
			end else begin
				$display("PASS k=%0d a=0x%04x b=0x%04x approx=0x%08x exact=0x%08x",
					LOA_K, in_a, in_b, p, exact_product);
			end
		end
	endtask

	initial begin
		errors = 0;
		seed = 32'h1badc0de;

		if ($value$plusargs("vcd=%s", vcd_file)) begin
			$dumpfile(vcd_file);
			$dumpvars(0, approx_mul16_loa_tb);
		end

		run_case(16'h0000, 16'h0000);
		run_case(16'h0001, 16'h0001);
		run_case(16'h000f, 16'h0003);
		run_case(16'h00ff, 16'h0002);
		run_case(16'h00ff, 16'h00ff);
		run_case(16'h1234, 16'h5678);
		run_case(16'ha5a5, 16'h5a5a);
		run_case(16'hffff, 16'h0001);
		run_case(16'hffff, 16'hffff);
		run_case(16'h8000, 16'h0002);

		for (idx = 0; idx < 50; idx = idx + 1) begin
			run_case($random(seed), $random(seed));
		end

		if (errors != 0) begin
			$display("TEST FAILED with %0d mismatches", errors);
			$finish(1);
		end

		$display("TEST PASSED for LOA_K=%0d", LOA_K);
		$finish;
	end
endmodule

build/sim/approx_mul16_loa_tb_k6.vcd
$date
	Sat Mar 28 15:00:42 2026
$end
$version
	Icarus Verilog
$end
$timescale
	1ps
$end
$scope module approx_mul16_loa_tb $end
$var wire 32 ! p [31:0] $end
$var parameter 32 " LOA_K $end
$var reg 16 # a [15:0] $end
$var reg 16 $ b [15:0] $end
$var reg 32 % exact_product [31:0] $end
$var reg 32 & expected [31:0] $end
$var reg 1024 ' vcd_file [1023:0] $end
$var integer 32 ( errors [31:0] $end
$var integer 32 ) idx [31:0] $end
$var integer 32 * seed [31:0] $end
$scope function approx_mul16_model $end
$var reg 16 + m0 [15:0] $end
$var reg 16 , m1 [15:0] $end
$var reg 16 - m2 [15:0] $end
$var reg 16 . m3 [15:0] $end
$var reg 24 / s0 [23:0] $end
$var reg 24 0 s1 [23:0] $end
$var reg 24 1 s2 [23:0] $end
$var reg 24 2 u0 [23:0] $end
$var reg 24 3 u1 [23:0] $end
$var reg 24 4 u2 [23:0] $end
$var reg 24 5 u3 [23:0] $end
$var reg 16 6 x [15:0] $end
$var reg 16 7 y [15:0] $end
$upscope $end
$scope function loa_sum24_model $end
$var reg 1 8 carry $end
$var reg 24 9 tmp [23:0] $end
$var reg 19 : upper [18:0] $end
$var reg 24 ; x [23:0] $end
$var reg 24 < y [23:0] $end
$var integer 32 = i [31:0] $end
$upscope $end
$scope function loa_sum_model $end
$var reg 1 > carry $end
$var reg 32 ? tmp [31:0] $end
$var reg 27 @ upper [26:0] $end
$var reg 32 A x [31:0] $end
$var reg 32 B y [31:0] $end
$var integer 32 C i [31:0] $end
$upscope $end
$scope function v2_mul8_model $end
$var reg 8 D x [7:0] $end
$var reg 8 E y [7:0] $end
$upscope $end
$scope module dut $end
$var wire 16 F a [15:0] $end
$var wire 16 G b [15:0] $end
$var wire 24 H upper3 [23:0] $end
$var wire 24 I upper2 [23:0] $end
$var wire 24 J upper1 [23:0] $end
$var wire 24 K upper0 [23:0] $end
$var wire 1 L unused_carry2 $end
$var wire 1 M unused_carry1 $end
$var wire 1 N unused_carry0 $end
$var wire 24 O stage2_sum [23:0] $end
$var wire 24 P stage1_sum [23:0] $end
$var wire 24 Q stage0_sum [23:0] $end
$var wire 32 R p [31:0] $end
$var wire 16 S m3 [15:0] $end
$var wire 16 T m2 [15:0] $end
$var wire 16 U m1 [15:0] $end
$var wire 16 V m0 [15:0] $end
$var parameter 32 W LOA_K $end
$var parameter 176 X V2_IMPLEMENTATION $end
$scope module u_add0 $end
$var wire 24 Y a [23:0] $end
$var wire 24 Z b [23:0] $end
$var wire 1 [ lower_carry $end
$var wire 6 \ lower_sum [5:0] $end
$var wire 19 ] upper_sum_ext [18:0] $end
$var wire 24 ^ sum [23:0] $end
$var wire 1 N carry_out $end
$var parameter 32 _ K $end
$var parameter 32 ` WIDTH $end
$upscope $end
$scope module u_add1 $end
$var wire 24 a a [23:0] $end
$var wire 24 b b [23:0] $end
$var wire 1 c lower_carry $end
$var wire 6 d lower_sum [5:0] $end
$var wire 19 e upper_sum_ext [18:0] $end
$var wire 24 f sum [23:0] $end
$var wire 1 M carry_out $end
$var parameter 32 g K $end
$var parameter 32 h WIDTH $end
$upscope $end
$scope module u_add2 $end
$var wire 24 i a [23:0] $end
$var wire 24 j b [23:0] $end
$var wire 1 k lower_carry $end
$var wire 6 l lower_sum [5:0] $end
$var wire 19 m upper_sum_ext [18:0] $end
$var wire 24 n sum [23:0] $end
$var wire 1 L carry_out $end
$var parameter 32 o K $end
$var parameter 32 p WIDTH $end
$upscope $end
$scope module u_m0 $end
$var wire 8 q a [7:0] $end
$var wire 8 r b [7:0] $end
$var wire 16 s p [15:0] $end
$var parameter 176 t V2_IMPLEMENTATION $end
$upscope $end
$scope module u_m1 $end
$var wire 8 u a [7:0] $end
$var wire 8 v b [7:0] $end
$var wire 16 w p [15:0] $end
$var parameter 176 x V2_IMPLEMENTATION $end
$upscope $end
$scope module u_m2 $end
$var wire 8 y a [7:0] $end
$var wire 8 z b [7:0] $end
$var wire 16 { p [15:0] $end
$var parameter 176 | V2_IMPLEMENTATION $end
$upscope $end
$scope module u_m3 $end
$var wire 8 } a [7:0] $end
$var wire 8 ~ b [7:0] $end
$var wire 16 !" p [15:0] $end
$var parameter 176 "" V2_IMPLEMENTATION $end
$upscope $end
$upscope $end
$scope task run_case $end
$var reg 16 #" in_a [15:0] $end
$var reg 16 $" in_b [15:0] $end
$upscope $end
$upscope $end
$enddefinitions $end
$comment Show the parameter values. $end
$dumpall
b101000001001100010000010100001101000101010010000100111101001100010001000100010101010010010111110100010101011000010000010100001101010100 ""
b101000001001100010000010100001101000101010010000100111101001100010001000100010101010010010111110100010101011000010000010100001101010100 |
b101000001001100010000010100001101000101010010000100111101001100010001000100010101010010010111110100010101011000010000010100001101010100 x
b101000001001100010000010100001101000101010010000100111101001100010001000100010101010010010111110100010101011000010000010100001101010100 t
b11000 p
b110 o
b11000 h
b110 g
b11000 `
b110 _
b101000001001100010000010100001101000101010010000100111101001100010001000100010101010010010111110100010101011000010000010100001101010100 X
b110 W
b110 "
$end
#0
$dumpvars
b0 $"
b0 #"
b0 !"
b0 ~
b0 }
b0 {
b0 z
b0 y
b0 w
b0 v
b0 u
b0 s
b0 r
b0 q
b0 n
b0 m
b0 l
0k
b0 j
b0 i
b0 f
b0 e
b0 d
0c
b0 b
b0 a
b0 ^
b0 ]
b0 \
0[
b0 Z
b0 Y
b0 V
b0 U
b0 T
b0 S
b0 R
b0 Q
b0 P
b0 O
0N
0M
0L
b0 K
b0 J
b0 I
b0 H
b0 G
b0 F
bx E
bx D
bx C
bx B
bx A
bx @
bx ?
x>
bx =
bx <
bx ;
bx :
bx 9
x8
bx 7
bx 6
bx 5
bx 4
bx 3
bx 2
bx 1
bx 0
bx /
bx .
bx -
bx ,
bx +
b11011101011011100000011011110 *
bx )
b0 (
b11000100111010101101001011011000110010000101111011100110110100101101101001011110110000101110000011100000111001001101111011110000101111101101101011101010110110000110001001101100101111101101100011011110110000101011111011101000110001001011111011010110011011000101110011101100110001101100100 '
bx &
bx %
b0 $
b0 #
b0 !
$end
#1000
b1 !
b1 R
b1 V
b1 s
b1 r
b1 z
b1 q
b1 u
b1 $
b1 G
b1 #
b1 F
b1 $"
b1 #"
b0 %
b0 &
b0 1
b0 0
b0 /
b0 :
08
b110 =
b0 9
b0 ;
b0 <
b0 5
b0 4
b0 3
b0 2
b0 .
b0 -
b0 ,
b0 +
b0 D
b0 E
b0 6
b0 7
#2000
b101101 !
b101101 R
b101101 V
b101101 s
b11 r
b11 z
b1111 q
b1111 u
b11 $
b11 G
b1111 #
b1111 F
b11 $"
b1111 #"
b1 %
b1 &
b110 =
b1 +
b0 D
b0 E
b1 6
b1 7
#3000
b1 O
b1 n
b1 l
b1 Q
b1 ^
b1 i
b1 \
b111111110 !
b111111110 R
b1 K
b1 Y
b111111110 V
b111111110 s
b10 r
b10 z
b11111111 q
b11111111 u
b10 $
b10 G
b11111111 #
b11111111 F
b10 $"
b11111111 #"
b101101 %
b101101 &
b110 =
b101101 +
b0 D
b0 E
b1111 6
b11 7
#4000
b11111110 O
b11111110 n
b111110 l
b11 m
b11111110 Q
b11111110 ^
b11111110 i
b111110 \
b11 ]
b1111111000000001 !
b1111111000000001 R
b11111110 K
b11111110 Y
b1111111000000001 V
b1111111000000001 s
b11111111 r
b11111111 z
b11111111 $
b11111111 G
b11111111 $"
b111111110 %
b111111110 &
b1 1
b1 /
b1 9
b110 =
b1 ;
b1 2
b111111110 +
b0 D
b0 E
b11111111 6
b10 7
#5000
b1100010010111111000 O
b1100010010111111000 n
b111000 l
1k
b1100010010111 m
b1000101111000 Q
b1000101111000 ^
b1000101111000 i
b1100001010001110000 P
b1100001010001110000 f
b1100001010001110000 j
b111000 \
b1000101 ]
b110000 d
b1100001010001 e
b110001001011111100001100000 !
b110001001011111100001100000 R
b11000 K
b11000 Y
b1000101111000 J
b1000101111000 Z
b1100000110000000000 H
b1100000110000000000 b
b100001110000 I
b100001110000 a
b1000101111000 U
b1000101111000 w
b11000001100 S
b11000001100 !"
b1100001100000 V
b1100001100000 s
b100001110000 T
b100001110000 {
b1111000 r
b1010110 v
b1111000 z
b1010110 ~
b110100 q
b110100 u
b10010 y
b10010 }
b101011001111000 $
b101011001111000 G
b1001000110100 #
b1001000110100 F
b101011001111000 $"
b1001000110100 #"
b1111111000000001 %
b1111111000000001 &
b11111110 1
b11111110 /
b11 :
b110 =
b11111110 9
b11111110 ;
b11111110 2
b1111111000000001 +
b0 D
b0 E
b11111111 7
#6000
b1110100111011000111010 O
b1110100111011000111010 n
b111010 l
0k
b1110100111011000 m
b11101000111010 Q
b11101000111010 ^
b11101000111010 i
b1110100011110000000010 P
b1110100011110000000010 f
b1110100011110000000010 j
b111010 \
b11101000 ]
b10 d
b1110100011110000 e
b111010011101100011101000000010 !
b111010011101100011101000000010 R
b111010 K
b111010 Y
b11101000000010 J
b11101000000010 Z
b11101000000010 I
b11101000000010 a
b1110100000001000000000 H
b1110100000001000000000 b
b11101000000010 V
b11101000000010 s
b11101000000010 U
b11101000000010 w
b11101000000010 T
b11101000000010 {
b11101000000010 S
b11101000000010 !"
b1011010 r
b1011010 v
b1011010 z
b1011010 ~
b10100101 q
b10100101 u
b10100101 y
b10100101 }
b101101001011010 $
b101101001011010 G
b1010010110100101 #
b1010010110100101 F
b101101001011010 $"
b1010010110100101 #"
b110001001100000000001100000 %
b110001001011111100001100000 &
b1100010010111111000 1
18
b1100001010001110000 0
b1000101111000 /
b1100010010111 :
b110 =
b1100010010111111000 9
b1000101111000 ;
b1100001010001110000 <
b1100000110000000000 5
b100001110000 4
b1000101111000 3
b11000 2
b11000001100 .
b100001110000 -
b1000101111000 ,
b1100001100000 +
b10010 D
b1010110 E
b1001000110100 6
b101011001111000 7
#7000
b11111111 O
b11111111 n
b111111 l
0k
b11 m
b0 Q
b0 ^
b0 i
b0 \
b11111111 P
b11111111 f
b11111111 j
b0 ]
b111111 d
b11 e
b1111111111111111 !
b1111111111111111 R
b0 K
b0 Y
b0 J
b0 Z
b11111111 I
b11111111 a
b0 H
b0 b
b11111111 V
b11111111 s
b0 U
b0 w
b11111111 T
b11111111 {
b0 S
b0 !"
b1 r
b0 v
b1 z
b0 ~
b11111111 q
b11111111 u
b11111111 y
b11111111 }
b1 $
b1 G
b1111111111111111 #
b1111111111111111 F
b1 $"
b1111111111111111 #"
b111010011101100011111000000010 %
b111010011101100011101000000010 &
b1110100111011000111010 1
b1110100011110000000010 0
b11101000111010 /
b1110100111011000 :
08
b110 =
b1110100111011000111010 9
b11101000111010 ;
b1110100011110000000010 <
b1110100000001000000000 5
b11101000000010 4
b11101000000010 3
b111010 2
b11101000000010 .
b11101000000010 -
b11101000000010 ,
b11101000000010 +
b10100101 D
b1011010 E
b1010010110100101 6
b101101001011010 7
#8000
b111111111111110111111111 O
b111111111111110111111111 n
b111111 l
b111111111111110111 m
b1111111011111111 Q
b1111111011111111 ^
b1111111011111111 i
b111111101111111100000001 P
b111111101111111100000001 f
b111111101111111100000001 j
b111111 \
b1111111011 ]
b1 d
b111111101111111100 e
b11111111111111011111111100000001 !
b11111111111111011111111100000001 R
b11111110 K
b11111110 Y
b1111111000000001 J
b1111111000000001 Z
b1111111000000001 I
b1111111000000001 a
b111111100000000100000000 H
b111111100000000100000000 b
b1111111000000001 V
b1111111000000001 s
b1111111000000001 U
b1111111000000001 w
b1111111000000001 T
b1111111000000001 {
b1111111000000001 S
b1111111000000001 !"
b11111111 r
b11111111 v
b11111111 z
b11111111 ~
b1111111111111111 $
b1111111111111111 G
b1111111111111111 $"
b1111111111111111 %
b1111111111111111 &
b11111111 1
b11111111 0
b0 /
b11 :
b110 =
b11111111 9
b0 ;
b11111111 <
b0 5
b11111111 4
b0 3
b0 2
b0 .
b11111111 -
b0 ,
b11111111 +
b11111111 D
b0 E
b1111111111111111 6
b1 7
#9000
b100000000 O
b100000000 n
b0 l
b100 m
b0 Q
b0 ^
b0 i
b100000000 P
b100000000 f
b100000000 j
b0 \
b0 ]
b0 d
b100 e
b10000000000000000 !
b10000000000000000 R
b0 K
b0 Y
b0 J
b0 Z
b100000000 I
b100000000 a
b0 H
b0 b
b0 V
b0 s
b0 U
b0 w
b100000000 T
b100000000 {
b0 S
b0 !"
b10 r
b0 v
b10 z
b0 ~
b0 q
b0 u
b10000000 y
b10000000 }
b10 $
b10 G
b1000000000000000 #
b1000000000000000 F
b10 $"
b1000000000000000 #"
b11111111111111100000000000000001 %
b11111111111111011111111100000001 &
b111111111111110111111111 1
b111111101111111100000001 0
b1111111011111111 /
b111111111111110111 :
b110 =
b111111111111110111111111 9
b1111111011111111 ;
b111111101111111100000001 <
b111111100000000100000000 5
b1111111000000001 4
b1111111000000001 3
b11111110 2
b1111111000000001 .
b1111111000000001 -
b1111111000000001 ,
b1111111000000001 +
b11111111 E
b1111111111111111 7
#10000
b1100101101110100111110 O
b1100101101110100111110 n
b111110 l
b1100101101110100 m
b10000110111010 Q
b10000110111010 ^
b10000110111010 i
b1100101011101110010100 P
b1100101011101110010100 f
b1100101011101110010100 j
b111010 \
b10000110 ]
b10100 d
b1100101011101110 e
b11000 K
b11000 Y
b110010110111010011111011111100 !
b110010110111010011111011111100 R
b10000110100010 J
b10000110100010 Z
b1100101001011000000000 H
b1100101001011000000000 b
b10010110010100 I
b10010110010100 a
b10000110100010 U
b10000110100010 w
b11001010010110 S
b11001010010110 !"
b1100011111100 V
b1100011111100 s
b10010110010100 T
b10010110010100 {
b110100 r
b1000110 v
b110100 z
b1000110 ~
b1111011 q
b1111011 u
b10111001 y
b10111001 }
b100011000110100 $
b100011000110100 G
b1011100101111011 #
b1011100101111011 F
b100011000110100 $"
b1011100101111011 #"
b11010000010110100010101011100 *
b0 )
b10000000000000000 %
b10000000000000000 &
b100000000 1
b100000000 0
b0 /
b100 :
b110 =
b100000000 9
b0 ;
b100000000 <
b0 5
b100000000 4
b0 3
b0 2
b0 .
b100000000 -
b0 ,
b0 +
b10000000 D
b0 E
b1000000000000000 6
b10 7
#11000
1k
b1000001101101001111110 O
b1000001101101001111110 n
b111110 l
b1000001101101001 m
b11100110111110 Q
b11100110111110 ^
b11100110111110 i
b1000001010000010111010 P
b1000001010000010111010 f
b1000001010000010111010 j
b111110 \
b11100110 ]
b111010 d
b1000001010000010 e
b100000110110100111111001110010 !
b100000110110100111111001110010 R
b110110 K
b110110 Y
b11100110011010 J
b11100110011010 Z
b1111010111010 I
b1111010111010 a
b1000001000001000000000 H
b1000001000001000000000 b
b11011001110010 V
b11011001110010 s
b11100110011010 U
b11100110011010 w
b1111010111010 T
b1111010111010 {
b10000010000010 S
b10000010000010 !"
b10001010 r
b10010010 v
b10001010 z
b10010010 ~
b1100101 q
b1100101 u
b111001 y
b111001 }
b1001001010001010 $
b1001001010001010 G
b11100101100101 #
b11100101100101 F
b1001001010001010 $"
b11100101100101 #"
b1000101011001111001000110001010 *
b1 )
b110010110111010100111011111100 %
b110010110111010011111011111100 &
b1100101101110100111110 1
b1100101011101110010100 0
b10000110111010 /
b1100101101110100 :
b110 =
b1100101101110100111110 9
b10000110111010 ;
b1100101011101110010100 <
b1100101001011000000000 5
b10010110010100 4
b10000110100010 3
b11000 2
b11001010010110 .
b10010110010100 -
b10000110100010 ,
b1100011111100 +
b10111001 D
b1000110 E
b1011100101111011 6
b100011000110100 7
#12000
b100011001000110011111101 O
b100011001000110011111101 n
b111101 l
0k
b100011001000110011 m
b1100101110110101 Q
b1100101110110101 ^
b1100101110110101 i
b100010111100000101011000 P
b100010111100000101011000 f
b100010111100000101011000 j
b110101 \
0[
b1100101110 ]
b11000 d
b100010111100000101 e
b10001100100011001111110101001100 !
b10001100100011001111110101001100 R
b11000101 K
b11000101 Y
b1100101011110101 J
b1100101011110101 Z
b1000011101011000 I
b1000011101011000 a
b100010110011101000000000 H
b100010110011101000000000 b
b1100010101001100 V
b1100010101001100 s
b1100101011110101 U
b1100101011110101 w
b1000011101011000 T
b1000011101011000 {
b1000101100111010 S
b1000101100111010 !"
b11110100 r
b11111011 v
b11110100 z
b11111011 ~
b11001111 q
b11001111 u
b10001110 y
b10001110 }
b1111101111110100 $
b1111101111110100 G
b1000111011001111 #
b1000111011001111 F
b1111101111110100 $"
b1000111011001111 #"
b11111010000111001111100011101000 *
b10 )
b100000110110101000101001110010 %
b100000110110100111111001110010 &
b1000001101101001111110 1
18
b1000001010000010111010 0
b11100110111110 /
b1000001101101001 :
b110 =
b1000001101101001111110 9
b11100110111110 ;
b1000001010000010111010 <
b1000001000001000000000 5
b1111010111010 4
b11100110011010 3
b110110 2
b10000010000010 .
b1111010111010 -
b11100110011010 ,
b11011001110010 +
b111001 D
b10010010 E
b11100101100101 6
b1001001010001010 7
#13000
b101111010101110011111 O
b101111010101110011111 n
b11111 l
b101111010101110 m
b110010011011101 Q
b110010011011101 ^
b110010011011101 i
b101110100011011000110 P
b101110100011011000110 f
b101110100011011000110 j
b11101 \
b110010011 ]
b110 d
b101110100011011 e
b10111101010111001111101011010 !
b10111101010111001111101011010 R
b1010001 K
b1010001 Y
b110010010001100 J
b110010010001100 Z
b1001011000110 I
b1001011000110 a
b101110011010000000000 H
b101110011010000000000 b
b101000101011010 V
b101000101011010 s
b110010010001100 U
b110010010001100 w
b1001011000110 T
b1001011000110 {
b1011100110100 S
b1011100110100 !"
b10110010 r
b11011100 v
b10110010 z
b11011100 ~
b1110101 q
b1110101 u
b11011 y
b11011 }
b1101110010110010 $
b1101110010110010 G
b1101101110101 #
b1101101110101 F
b1101110010110010 $"
b1101101110101 #"
b1011001000111111101101011110110 *
b11 )
b10001100100011010001001001001100 %
b10001100100011001111110101001100 &
b100011001000110011111101 1
b100010111100000101011000 0
b1100101110110101 /
b100011001000110011 :
08
b110 =
b100011001000110011111101 9
b1100101110110101 ;
b100010111100000101011000 <
b100010110011101000000000 5
b1000011101011000 4
b1100101011110101 3
b11000101 2
b1000101100111010 .
b1000011101011000 -
b1100101011110101 ,
b1100010101001100 +
b10001110 D
b11111011 E
b1000111011001111 6
b1111101111110100 7
#14000
b11011110110111010111101 O
b11011110110111010111101 n
b111101 l
b11011110110111010 m
1[
b101101001111101 Q
b101101001111101 ^
b101101001111101 i
b11011110001010001000101 P
b11011110001010001000101 f
b11011110001010001000101 j
b111101 \
b101101001 ]
b101 d
b11011110001010001 e
b1101111011011101011110111001101 !
b1101111011011101011110111001101 R
b101101 K
b101101 Y
b101101000111100 J
b101101000111100 Z
b11100001000101 I
b11100001000101 a
b11011101101110000000000 H
b11011101101110000000000 b
b10110111001101 V
b10110111001101 s
b101101000111100 U
b101101000111100 w
b11100001000101 T
b11100001000101 {
b110111011011100 S
b110111011011100 !"
b1000011 r
b10000100 v
b1000011 z
b10000100 ~
b10101111 q
b10101111 u
b11010111 y
b11010111 }
b1000010001000011 $
b1000010001000011 G
b1101011110101111 #
b1101011110101111 F
b1000010001000011 $"
b1101011110101111 #"
b100001100110001000001100110100 *
b100 )
b10111101010111010001101011010 %
b10111101010111001111101011010 &
b101111010101110011111 1
b101110100011011000110 0
b110010011011101 /
b101111010101110 :
b110 =
b101111010101110011111 9
b110010011011101 ;
b101110100011011000110 <
b101110011010000000000 5
b1001011000110 4
b110010010001100 3
b1010001 2
b1011100110100 .
b1001011000110 -
b110010010001100 ,
b101000101011010 +
b11011 D
b11011100 E
b1101101110101 6
b1101110010110010 7
